[[{"id":"plant_prop","x":124,"y":57,"angle":0,"scale":1},{"id":"painting_2_prop","x":39,"y":594,"angle":0,"scale":1},{"id":"painting_3_prop","x":37,"y":418,"angle":0,"scale":1},{"id":"painting_1_prop","x":347,"y":419,"angle":0,"scale":1},{"id":"painting_1_prop","x":59,"y":150,"angle":0,"scale":1},{"id":"painting_2_prop","x":191,"y":151,"angle":0,"scale":1},{"id":"painting_3_prop","x":327,"y":148,"angle":0,"scale":1},{"id":"plant_prop","x":59,"y":185,"angle":0,"scale":1},{"id":"plant_prop","x":165,"y":185,"angle":0,"scale":1},{"id":"plant_prop","x":217,"y":185,"angle":0,"scale":1},{"id":"chair_prop","x":189,"y":185,"angle":0,"scale":1},{"id":"chair_prop","x":76,"y":185,"angle":0,"scale":1},{"id":"chair_prop","x":297,"y":185,"angle":0,"scale":1},{"id":"plant_prop","x":320,"y":185,"angle":0,"scale":1},{"id":"plant_prop","x":141,"y":281,"angle":0,"scale":1},{"id":"plant_prop","x":243,"y":281,"angle":0,"scale":1},{"id":"copier_prop","x":162,"y":409,"angle":0,"scale":1},{"id":"copier_prop","x":220,"y":409,"angle":0,"scale":1},{"id":"plant_prop","x":133,"y":665,"angle":0,"scale":1},{"id":"plant_prop","x":236,"y":561,"angle":0,"scale":1},{"id":"chair_prop","x":128,"y":569,"angle":0,"scale":1},{"id":"chair_prop","x":121,"y":777,"angle":0,"scale":1},{"id":"chair_prop","x":240,"y":777,"angle":0,"scale":1},{"id":"plant_prop","x":139,"y":777,"angle":0,"scale":1}],[{"id":"ceo","x":51,"y":186,"angle":0,"scale":1},{"id":"ceo","x":83,"y":186,"angle":0,"scale":1},{"id":"ceo","x":149,"y":186,"angle":0,"scale":1},{"id":"ceo","x":197,"y":186,"angle":0,"scale":1},{"id":"ceo","x":243,"y":186,"angle":0,"scale":1},{"id":"ceo","x":305,"y":186,"angle":0,"scale":1},{"id":"ceo","x":334,"y":186,"angle":0,"scale":1},{"id":"maintenance_guy","x":25,"y":611,"angle":0,"scale":1},{"id":"burglar","x":352,"y":595,"angle":0,"scale":1},{"id":"supervillain","x":42,"y":441,"angle":0,"scale":1},{"id":"superhero","x":351,"y":441,"angle":0,"scale":1},{"id":"robot","x":67,"y":635,"angle":0,"scale":1},{"id":"businessman","x":129,"y":779,"angle":0,"scale":1},{"id":"businessman","x":158,"y":779,"angle":0,"scale":1},{"id":"businessman","x":203,"y":779,"angle":0,"scale":1},{"id":"businessman","x":249,"y":779,"angle":0,"scale":1},{"id":"bank_manager","x":150,"y":250,"angle":0,"scale":1},{"id":"bank_manager","x":193,"y":250,"angle":0,"scale":1},{"id":"bank_manager","x":242,"y":250,"angle":0,"scale":1},{"id":"bank_manager","x":119,"y":282,"angle":0,"scale":1},{"id":"bank_manager","x":158,"y":282,"angle":0,"scale":1},{"id":"bank_manager","x":233,"y":282,"angle":0,"scale":1},{"id":"bank_manager","x":274,"y":282,"angle":0,"scale":1},{"id":"old_lady","x":10,"y":777,"angle":0,"scale":1},{"id":"old_lady","x":60,"y":777,"angle":0,"scale":1},{"id":"old_lady","x":326,"y":776,"angle":0,"scale":1},{"id":"old_lady","x":362,"y":776,"angle":0,"scale":1},{"id":"player","x":196,"y":754,"angle":0,"scale":1},{"id":"robot","x":240,"y":691,"angle":0,"scale":1},{"id":"robot","x":249,"y":515,"angle":0,"scale":1},{"id":"robot","x":123,"y":531,"angle":0,"scale":1},{"id":"bank_manager","x":137,"y":282,"angle":0,"scale":1},{"id":"bank_manager","x":251,"y":282,"angle":0,"scale":1},{"id":"security_guard","x":114,"y":379,"angle":0,"scale":1},{"id":"security_guard","x":139,"y":379,"angle":0,"scale":1},{"id":"security_guard","x":163,"y":379,"angle":0,"scale":1},{"id":"security_guard","x":240,"y":379,"angle":0,"scale":1},{"id":"security_guard","x":260,"y":379,"angle":0,"scale":1},{"id":"security_guard","x":281,"y":379,"angle":0,"scale":1},{"id":"security_guard","x":143,"y":347,"angle":0,"scale":1},{"id":"security_guard","x":195,"y":347,"angle":0,"scale":1},{"id":"security_guard","x":251,"y":347,"angle":0,"scale":1},{"id":"security_guard","x":166,"y":315,"angle":0,"scale":1},{"id":"security_guard","x":199,"y":315,"angle":0,"scale":1},{"id":"security_guard","x":229,"y":315,"angle":0,"scale":1},{"id":"businessman","x":116,"y":443,"angle":0,"scale":1},{"id":"businessman","x":142,"y":443,"angle":0,"scale":1},{"id":"businessman","x":167,"y":443,"angle":0,"scale":1},{"id":"businessman","x":232,"y":443,"angle":0,"scale":1},{"id":"businessman","x":261,"y":443,"angle":0,"scale":1},{"id":"businessman","x":283,"y":443,"angle":0,"scale":1},{"id":"businessman","x":143,"y":411,"angle":0,"scale":1},{"id":"businessman","x":199,"y":411,"angle":0,"scale":1},{"id":"businessman","x":249,"y":411,"angle":0,"scale":1}],[{"id":"desk_prop","x":123,"y":777,"angle":0,"scale":1},{"id":"desk_prop","x":242,"y":777,"angle":0,"scale":1},{"id":"desk_prop","x":226,"y":625,"angle":0,"scale":1},{"id":"desk_prop","x":131,"y":569,"angle":0,"scale":1},{"id":"desk_prop","x":129,"y":497,"angle":0,"scale":1},{"id":"desk_prop","x":190,"y":185,"angle":0,"scale":1},{"id":"desk_prop","x":78,"y":185,"angle":0,"scale":1},{"id":"desk_prop","x":301,"y":185,"angle":0,"scale":1}],[]]